{
  "parent": "minecraft:recipes/root",
  "criteria": {
    "has_polished_tripslate": {
      "conditions": {
        "items": [
          {
            "items": "litavis:polished_tripslate"
          }
        ]
      },
      "trigger": "minecraft:inventory_changed"
    },
    "has_the_recipe": {
      "conditions": {
        "recipe": "litavis:tripslate_bricks_crafting"
      },
      "trigger": "minecraft:recipe_unlocked"
    }
  },
  "requirements": [
    [
      "has_the_recipe",
      "has_polished_tripslate"
    ]
  ],
  "rewards": {
    "recipes": [
      "litavis:tripslate_bricks_crafting"
    ]
  }
}